README.md
setup.py
pypi_name/__init__.py
pypi_name/check.py
pypi_name.egg-info/PKG-INFO
pypi_name.egg-info/SOURCES.txt
pypi_name.egg-info/dependency_links.txt
pypi_name.egg-info/requires.txt
pypi_name.egg-info/top_level.txt