Metadata-Version: 2.1
Name: pypi_name
Version: 1.0.0
Summary: Check whether a package name is available on PyPI
Home-page: https://yoginth.com
Author: Yoginth
Author-email: me@yoginth.com
License: UNKNOWN
Project-URL: Source, https://gitlab.com/yoginth/pypi_name
Platform: UNKNOWN
Classifier: Programming Language :: Python
Classifier: Natural Language :: English
Classifier: Environment :: Plugins
Classifier: Operating System :: OS Independent
Classifier: Intended Audience :: Developers
Classifier: License :: OSI Approved :: MIT License
